geonmolib/__init__.py
geonmolib/datasetinfo.py
geonmolib/xrdrepair.py
geonmolib-0.1.3.dist-info/LICENSE
geonmolib-0.1.3.dist-info/WHEEL
geonmolib-0.1.3.dist-info/METADATA
geonmolib-0.1.3.dist-info/RECORD
